CHANGES.txt
LICENCE.txt
MANIFEST.in
README.md
setup.py
django_eggplant.egg-info/PKG-INFO
django_eggplant.egg-info/SOURCES.txt
django_eggplant.egg-info/dependency_links.txt
django_eggplant.egg-info/not-zip-safe
django_eggplant.egg-info/requires.txt
django_eggplant.egg-info/top_level.txt
eggplant/__init__.py
eggplant/exceptions.py
eggplant/tests.py
eggplant/auth/__init__.py
eggplant/auth/permissions.py
eggplant/auth/signature.py
eggplant/auth/token.py
eggplant/auth/backends/__init__.py
eggplant/constants/__init__.py
eggplant/constants/defaults.py
eggplant/constants/settings.py
eggplant/context_processors/__init__.py
eggplant/datatype/__init__.py
eggplant/datetime/__init__.py
eggplant/fabfile/__init__.py
eggplant/forms/__init__.py
eggplant/forms/fields/__init__.py
eggplant/forms/fields/html5.py
eggplant/forms/fields/json_field.py
eggplant/forms/widgets/__init__.py
eggplant/forms/widgets/html5.py
eggplant/middleware/__init__.py
eggplant/middleware/put.py
eggplant/middleware/tls.py
eggplant/models/__init__.py
eggplant/models/dictionary.py
eggplant/models/signature.py
eggplant/models/timestamp.py
eggplant/models/fields/__init__.py
eggplant/models/fields/json_field.py
eggplant/utils/__init__.py
eggplant/utils/json.py
eggplant/utils/string.py
eggplant/utils/timezone.py
eggplant/utils/url.py
eggplant/validators/__init__.py
eggplant/validators/iterator.py
eggplant/validators/number.py
eggplant/validators/string.py
eggplant/views/__init__.py
eggplant/views/exceptions.py
eggplant/views/functions.py
eggplant/views/api/__init__.py
eggplant/views/api/model.py
eggplant/views/decorators/__init__.py
eggplant/views/decorators/request_key.py
eggplant/views/decorators/ssl.py
eggplant/views/web/__init__.py